energy_machines_jupyter_reports/__init__.py
energy_machines_jupyter_reports/_version.py
energy_machines_jupyter_reports/labextension/package.json
energy_machines_jupyter_reports/labextension/schemas/energy_machines_jupyter_reports/package.json.orig
energy_machines_jupyter_reports/labextension/schemas/energy_machines_jupyter_reports/settings.json
energy_machines_jupyter_reports/labextension/static/117.01da285cfa8501998cac.js
energy_machines_jupyter_reports/labextension/static/151.6ddd31acf3ed790fbf16.js
energy_machines_jupyter_reports/labextension/static/151.6ddd31acf3ed790fbf16.js.LICENSE.txt
energy_machines_jupyter_reports/labextension/static/184.a11b15cf5fab1cddf944.js
energy_machines_jupyter_reports/labextension/static/184.a11b15cf5fab1cddf944.js.LICENSE.txt
energy_machines_jupyter_reports/labextension/static/23.5da48b8299e64c3a4878.js
energy_machines_jupyter_reports/labextension/static/253.0867d66be87a54abbfe6.js
energy_machines_jupyter_reports/labextension/static/253.0867d66be87a54abbfe6.js.LICENSE.txt
energy_machines_jupyter_reports/labextension/static/286.64a4b229d5ddb665f63f.js
energy_machines_jupyter_reports/labextension/static/356.f8cc3ca5d8814dc1845f.js
energy_machines_jupyter_reports/labextension/static/392.8d01ea3f37e190204e74.js
energy_machines_jupyter_reports/labextension/static/486.947faf24ee524a6aca41.js
energy_machines_jupyter_reports/labextension/static/486.947faf24ee524a6aca41.js.LICENSE.txt
energy_machines_jupyter_reports/labextension/static/534.df69baa77a780e7d89e9.js
energy_machines_jupyter_reports/labextension/static/573.7e6e21d8aca4f0e87155.js
energy_machines_jupyter_reports/labextension/static/658.5d844a6fa377627a3ae8.js
energy_machines_jupyter_reports/labextension/static/706.d4867c7e093074a48ae4.js
energy_machines_jupyter_reports/labextension/static/706.d4867c7e093074a48ae4.js.LICENSE.txt
energy_machines_jupyter_reports/labextension/static/728.eb460e466454a2fafe83.js
energy_machines_jupyter_reports-0.1.0.dist-info/LICENSE
energy_machines_jupyter_reports-0.1.0.dist-info/METADATA
energy_machines_jupyter_reports-0.1.0.dist-info/WHEEL
energy_machines_jupyter_reports-0.1.0.dist-info/top_level.txt
energy_machines_jupyter_reports-0.1.0.dist-info/RECORD
