Metadata-Version: 2.1
Name: energy-machines-jupyter-reports
Version: 0.1.0
Summary: A JupyterLab extension developed by Energy Machines for use with reports from THMI.
Home-page: https://github.com/cybermental/thmi-jupyter-reports
Author: energymachines.cloud
License: BSD-3-Clause
Keywords: Jupyter,JupyterLab,JupyterLab3
Platform: Linux
Platform: Mac OS X
Platform: Windows
Classifier: License :: OSI Approved :: BSD License
Classifier: Programming Language :: Python
Classifier: Programming Language :: Python :: 3
Classifier: Programming Language :: Python :: 3.6
Classifier: Programming Language :: Python :: 3.7
Classifier: Programming Language :: Python :: 3.8
Classifier: Framework :: Jupyter
Requires-Python: >=3.6
License-File: LICENSE
Requires-Dist: jupyterlab ==3.*,>=3.0.0rc13
